{"Teams":[{"Rank":1,"Name":"Brazil","TotalPoints":0.0,"PreviousPoints":842,"MovePosition":0,"FlagUrl":"http://img.fifa.com/images/flags/4/bra.png"},{"Rank":2,"Name":"France","TotalPoints":0.0,"PreviousPoints":791,"MovePosition":0,"FlagUrl":"http://img.fifa.com/images/flags/4/fra.png"},{"Rank":3,"Name":"Argentina","TotalPoints":0.0,"PreviousPoints":785,"MovePosition":0,"FlagUrl":"http://img.fifa.com/images/flags/4/arg.png"},{"Rank":4,"Name":"Czech Republic","TotalPoints":0.0,"PreviousPoints":777,"MovePosition":0,"FlagUrl":"http://img.fifa.com/images/flags/4/cze.png"},{"Rank":5,"Name":"Spain","TotalPoints":0.0,"PreviousPoints":764,"MovePosition":0,"FlagUrl":"http://img.fifa.com/images/flags/4/esp.png"},{"Rank":6,"Name":"Netherlands","TotalPoints":0.0,"PreviousPoints":757,"MovePosition":0,"FlagUrl":"http://img.fifa.com/images/flags/4/ned.png"},{"Rank":6,"Name":"Mexico","TotalPoints":0.0,"PreviousPoints":753,"MovePosition":1,"FlagUrl":"http://img.fifa.com/images/flags/4/mex.png"},{"Rank":8,"Name":"England","TotalPoints":0.0,"PreviousPoints":751,"MovePosition":0,"FlagUrl":"http://img.fifa.com/images/flags/4/eng.png"},{"Rank":9,"Name":"Portugal","TotalPoints":0.0,"PreviousPoints":747,"MovePosition":0,"FlagUrl":"http://img.fifa.com/images/flags/4/por.png"},{"Rank":10,"Name":"Italy","TotalPoints":0.0,"PreviousPoints":738,"MovePosition":0,"FlagUrl":"http://img.fifa.com/images/flags/4/ita.png"},{"Rank":11,"Name":"USA","TotalPoints":0.0,"PreviousPoints":726,"MovePosition":0,"FlagUrl":"http://img.fifa.com/images/flags/4/usa.png"},{"Rank":12,"Name":"Republic of Ireland","TotalPoints":0.0,"PreviousPoints":716,"MovePosition":0,"FlagUrl":"http://img.fifa.com/images/flags/4/irl.png"},{"Rank":13,"Name":"Sweden","TotalPoints":0.0,"PreviousPoints":715,"MovePosition":0,"FlagUrl":"http://img.fifa.com/images/flags/4/swe.png"},{"Rank":13,"Name":"Greece","TotalPoints":0.0,"PreviousPoints":706,"MovePosition":5,"FlagUrl":"http://img.fifa.com/images/flags/4/gre.png"},{"Rank":15,"Name":"Denmark","TotalPoints":0.0,"PreviousPoints":711,"MovePosition":-1,"FlagUrl":"http://img.fifa.com/images/flags/4/den.png"},{"Rank":15,"Name":"Turkey","TotalPoints":0.0,"PreviousPoints":711,"MovePosition":-1,"FlagUrl":"http://img.fifa.com/images/flags/4/tur.png"},{"Rank":17,"Name":"Germany","TotalPoints":0.0,"PreviousPoints":710,"MovePosition":-1,"FlagUrl":"http://img.fifa.com/images/flags/4/ger.png"},{"Rank":18,"Name":"Uruguay","TotalPoints":0.0,"PreviousPoints":707,"MovePosition":-1,"FlagUrl":"http://img.fifa.com/images/flags/4/uru.png"},{"Rank":18,"Name":"Japan","TotalPoints":0.0,"PreviousPoints":703,"MovePosition":1,"FlagUrl":"http://img.fifa.com/images/flags/4/jpn.png"},{"Rank":20,"Name":"Iran","TotalPoints":0.0,"PreviousPoints":695,"MovePosition":0,"FlagUrl":"http://img.fifa.com/images/flags/4/irn.png"},{"Rank":21,"Name":"Korea Republic","TotalPoints":0.0,"PreviousPoints":689,"MovePosition":0,"FlagUrl":"http://img.fifa.com/images/flags/4/kor.png"},{"Rank":21,"Name":"Nigeria","TotalPoints":0.0,"PreviousPoints":689,"MovePosition":0,"FlagUrl":"http://img.fifa.com/images/flags/4/nga.png"},{"Rank":23,"Name":"Cameroon","TotalPoints":0.0,"PreviousPoints":676,"MovePosition":0,"FlagUrl":"http://img.fifa.com/images/flags/4/cmr.png"},{"Rank":23,"Name":"Croatia","TotalPoints":0.0,"PreviousPoints":676,"MovePosition":0,"FlagUrl":"http://img.fifa.com/images/flags/4/cro.png"},{"Rank":25,"Name":"Poland","TotalPoints":0.0,"PreviousPoints":671,"MovePosition":0,"FlagUrl":"http://img.fifa.com/images/flags/4/pol.png"},{"Rank":26,"Name":"Colombia","TotalPoints":0.0,"PreviousPoints":670,"MovePosition":0,"FlagUrl":"http://img.fifa.com/images/flags/4/col.png"},{"Rank":27,"Name":"Costa Rica","TotalPoints":0.0,"PreviousPoints":668,"MovePosition":0,"FlagUrl":"http://img.fifa.com/images/flags/4/crc.png"},{"Rank":28,"Name":"Romania","TotalPoints":0.0,"PreviousPoints":664,"MovePosition":0,"FlagUrl":"http://img.fifa.com/images/flags/4/rou.png"},{"Rank":29,"Name":"Paraguay","TotalPoints":0.0,"PreviousPoints":661,"MovePosition":0,"FlagUrl":"http://img.fifa.com/images/flags/4/par.png"},{"Rank":30,"Name":"Saudi Arabia","TotalPoints":0.0,"PreviousPoints":657,"MovePosition":0,"FlagUrl":"http://img.fifa.com/images/flags/4/ksa.png"},{"Rank":31,"Name":"Senegal","TotalPoints":0.0,"PreviousPoints":657,"MovePosition":-1,"FlagUrl":"http://img.fifa.com/images/flags/4/sen.png"},{"Rank":32,"Name":"Egypt","TotalPoints":0.0,"PreviousPoints":648,"MovePosition":1,"FlagUrl":"http://img.fifa.com/images/flags/4/egy.png"},{"Rank":32,"Name":"Russia","TotalPoints":0.0,"PreviousPoints":651,"MovePosition":0,"FlagUrl":"http://img.fifa.com/images/flags/4/rus.png"},{"Rank":34,"Name":"Morocco","TotalPoints":0.0,"PreviousPoints":646,"MovePosition":0,"FlagUrl":"http://img.fifa.com/images/flags/4/mar.png"},{"Rank":35,"Name":"Norway","TotalPoints":0.0,"PreviousPoints":632,"MovePosition":1,"FlagUrl":"http://img.fifa.com/images/flags/4/nor.png"},{"Rank":36,"Name":"Tunisia","TotalPoints":0.0,"PreviousPoints":633,"MovePosition":-1,"FlagUrl":"http://img.fifa.com/images/flags/4/tun.png"},{"Rank":37,"Name":"Ecuador","TotalPoints":0.0,"PreviousPoints":616,"MovePosition":2,"FlagUrl":"http://img.fifa.com/images/flags/4/ecu.png"},{"Rank":38,"Name":"Finland","TotalPoints":0.0,"PreviousPoints":607,"MovePosition":5,"FlagUrl":"http://img.fifa.com/images/flags/4/fin.png"},{"Rank":39,"Name":"Bulgaria","TotalPoints":0.0,"PreviousPoints":623,"MovePosition":-2,"FlagUrl":"http://img.fifa.com/images/flags/4/bul.png"},{"Rank":40,"Name":"South Africa","TotalPoints":0.0,"PreviousPoints":621,"MovePosition":-2,"FlagUrl":"http://img.fifa.com/images/flags/4/rsa.png"},{"Rank":41,"Name":"Jordan","TotalPoints":0.0,"PreviousPoints":611,"MovePosition":-1,"FlagUrl":"http://img.fifa.com/images/flags/4/jor.png"},{"Rank":41,"Name":"Côte d'Ivoire","TotalPoints":0.0,"PreviousPoints":610,"MovePosition":0,"FlagUrl":"http://img.fifa.com/images/flags/4/civ.png"},{"Rank":43,"Name":"Slovenia","TotalPoints":0.0,"PreviousPoints":608,"MovePosition":-1,"FlagUrl":"http://img.fifa.com/images/flags/4/svn.png"},{"Rank":44,"Name":"Belgium","TotalPoints":0.0,"PreviousPoints":600,"MovePosition":0,"FlagUrl":"http://img.fifa.com/images/flags/4/bel.png"},{"Rank":44,"Name":"Iraq","TotalPoints":0.0,"PreviousPoints":600,"MovePosition":0,"FlagUrl":"http://img.fifa.com/images/flags/4/irq.png"},{"Rank":46,"Name":"Serbia and Montenegro","TotalPoints":0.0,"PreviousPoints":599,"MovePosition":0,"FlagUrl":"http://img.fifa.com/images/flags/4/scg.png"},{"Rank":46,"Name":"Jamaica","TotalPoints":0.0,"PreviousPoints":598,"MovePosition":1,"FlagUrl":"http://img.fifa.com/images/flags/4/jam.png"},{"Rank":48,"Name":"Uzbekistan","TotalPoints":0.0,"PreviousPoints":598,"MovePosition":-1,"FlagUrl":"http://img.fifa.com/images/flags/4/uzb.png"},{"Rank":49,"Name":"Ukraine","TotalPoints":0.0,"PreviousPoints":580,"MovePosition":8,"FlagUrl":"http://img.fifa.com/images/flags/4/ukr.png"},{"Rank":49,"Name":"Switzerland","TotalPoints":0.0,"PreviousPoints":589,"MovePosition":2,"FlagUrl":"http://img.fifa.com/images/flags/4/sui.png"},{"Rank":51,"Name":"Israel","TotalPoints":0.0,"PreviousPoints":595,"MovePosition":-2,"FlagUrl":"http://img.fifa.com/images/flags/4/isr.png"},{"Rank":52,"Name":"Bahrain","TotalPoints":0.0,"PreviousPoints":592,"MovePosition":-2,"FlagUrl":"http://img.fifa.com/images/flags/4/bhr.png"},{"Rank":53,"Name":"Mali","TotalPoints":0.0,"PreviousPoints":589,"MovePosition":-2,"FlagUrl":"http://img.fifa.com/images/flags/4/mli.png"},{"Rank":54,"Name":"Slovakia","TotalPoints":0.0,"PreviousPoints":587,"MovePosition":-1,"FlagUrl":"http://img.fifa.com/images/flags/4/svk.png"},{"Rank":55,"Name":"China PR","TotalPoints":0.0,"PreviousPoints":585,"MovePosition":-1,"FlagUrl":"http://img.fifa.com/images/flags/4/chn.png"},{"Rank":56,"Name":"Kuwait","TotalPoints":0.0,"PreviousPoints":584,"MovePosition":-1,"FlagUrl":"http://img.fifa.com/images/flags/4/kuw.png"},{"Rank":57,"Name":"Oman","TotalPoints":0.0,"PreviousPoints":583,"MovePosition":-1,"FlagUrl":"http://img.fifa.com/images/flags/4/oma.png"},{"Rank":58,"Name":"Honduras","TotalPoints":0.0,"PreviousPoints":574,"MovePosition":1,"FlagUrl":"http://img.fifa.com/images/flags/4/hon.png"},{"Rank":58,"Name":"Australia","TotalPoints":0.0,"PreviousPoints":576,"MovePosition":0,"FlagUrl":"http://img.fifa.com/images/flags/4/aus.png"},{"Rank":60,"Name":"Zimbabwe","TotalPoints":0.0,"PreviousPoints":572,"MovePosition":0,"FlagUrl":"http://img.fifa.com/images/flags/4/zim.png"},{"Rank":61,"Name":"Venezuela","TotalPoints":0.0,"PreviousPoints":562,"MovePosition":2,"FlagUrl":"http://img.fifa.com/images/flags/4/ven.png"},{"Rank":62,"Name":"Trinidad and Tobago","TotalPoints":0.0,"PreviousPoints":568,"MovePosition":-1,"FlagUrl":"http://img.fifa.com/images/flags/4/tri.png"},{"Rank":63,"Name":"Libya","TotalPoints":0.0,"PreviousPoints":566,"MovePosition":-1,"FlagUrl":"http://img.fifa.com/images/flags/4/lby.png"},{"Rank":64,"Name":"Belarus","TotalPoints":0.0,"PreviousPoints":554,"MovePosition":4,"FlagUrl":"http://img.fifa.com/images/flags/4/blr.png"},{"Rank":65,"Name":"Wales","TotalPoints":0.0,"PreviousPoints":554,"MovePosition":3,"FlagUrl":"http://img.fifa.com/images/flags/4/wal.png"},{"Rank":65,"Name":"Hungary","TotalPoints":0.0,"PreviousPoints":562,"MovePosition":-2,"FlagUrl":"http://img.fifa.com/images/flags/4/hun.png"},{"Rank":67,"Name":"Qatar","TotalPoints":0.0,"PreviousPoints":561,"MovePosition":-2,"FlagUrl":"http://img.fifa.com/images/flags/4/qat.png"},{"Rank":67,"Name":"Latvia","TotalPoints":0.0,"PreviousPoints":560,"MovePosition":-1,"FlagUrl":"http://img.fifa.com/images/flags/4/lva.png"},{"Rank":69,"Name":"Peru","TotalPoints":0.0,"PreviousPoints":557,"MovePosition":-2,"FlagUrl":"http://img.fifa.com/images/flags/4/per.png"},{"Rank":70,"Name":"Guatemala","TotalPoints":0.0,"PreviousPoints":554,"MovePosition":-2,"FlagUrl":"http://img.fifa.com/images/flags/4/gua.png"},{"Rank":71,"Name":"Cuba","TotalPoints":0.0,"PreviousPoints":549,"MovePosition":1,"FlagUrl":"http://img.fifa.com/images/flags/4/cub.png"},{"Rank":71,"Name":"Zambia","TotalPoints":0.0,"PreviousPoints":552,"MovePosition":0,"FlagUrl":"http://img.fifa.com/images/flags/4/zam.png"},{"Rank":73,"Name":"Angola","TotalPoints":0.0,"PreviousPoints":545,"MovePosition":0,"FlagUrl":"http://img.fifa.com/images/flags/4/ang.png"},{"Rank":74,"Name":"Chile","TotalPoints":0.0,"PreviousPoints":533,"MovePosition":1,"FlagUrl":"http://img.fifa.com/images/flags/4/chi.png"},{"Rank":75,"Name":"Algeria","TotalPoints":0.0,"PreviousPoints":538,"MovePosition":-1,"FlagUrl":"http://img.fifa.com/images/flags/4/alg.png"},{"Rank":76,"Name":"Congo DR","TotalPoints":0.0,"PreviousPoints":527,"MovePosition":2,"FlagUrl":"http://img.fifa.com/images/flags/4/cod.png"},{"Rank":77,"Name":"Kenya","TotalPoints":0.0,"PreviousPoints":533,"MovePosition":-2,"FlagUrl":"http://img.fifa.com/images/flags/4/ken.png"},{"Rank":78,"Name":"Bosnia and Herzegovina","TotalPoints":0.0,"PreviousPoints":526,"MovePosition":1,"FlagUrl":"http://img.fifa.com/images/flags/4/bih.png"},{"Rank":79,"Name":"Ghana","TotalPoints":0.0,"PreviousPoints":528,"MovePosition":-2,"FlagUrl":"http://img.fifa.com/images/flags/4/gha.png"},{"Rank":80,"Name":"Estonia","TotalPoints":0.0,"PreviousPoints":525,"MovePosition":0,"FlagUrl":"http://img.fifa.com/images/flags/4/est.png"},{"Rank":80,"Name":"Thailand","TotalPoints":0.0,"PreviousPoints":525,"MovePosition":0,"FlagUrl":"http://img.fifa.com/images/flags/4/tha.png"},{"Rank":82,"Name":"Austria","TotalPoints":0.0,"PreviousPoints":522,"MovePosition":0,"FlagUrl":"http://img.fifa.com/images/flags/4/aut.png"},{"Rank":83,"Name":"United Arab Emirates","TotalPoints":0.0,"PreviousPoints":521,"MovePosition":0,"FlagUrl":"http://img.fifa.com/images/flags/4/uae.png"},{"Rank":84,"Name":"Burkina Faso","TotalPoints":0.0,"PreviousPoints":519,"MovePosition":0,"FlagUrl":"http://img.fifa.com/images/flags/4/bfa.png"},{"Rank":85,"Name":"Canada","TotalPoints":0.0,"PreviousPoints":512,"MovePosition":5,"FlagUrl":"http://img.fifa.com/images/flags/4/can.png"},{"Rank":86,"Name":"Syria","TotalPoints":0.0,"PreviousPoints":516,"MovePosition":-1,"FlagUrl":"http://img.fifa.com/images/flags/4/syr.png"},{"Rank":87,"Name":"Albania","TotalPoints":0.0,"PreviousPoints":515,"MovePosition":-1,"FlagUrl":"http://img.fifa.com/images/flags/4/alb.png"},{"Rank":87,"Name":"Scotland","TotalPoints":0.0,"PreviousPoints":515,"MovePosition":-1,"FlagUrl":"http://img.fifa.com/images/flags/4/sco.png"},{"Rank":87,"Name":"Guinea","TotalPoints":0.0,"PreviousPoints":514,"MovePosition":1,"FlagUrl":"http://img.fifa.com/images/flags/4/gui.png"},{"Rank":90,"Name":"Togo","TotalPoints":0.0,"PreviousPoints":513,"MovePosition":-1,"FlagUrl":"http://img.fifa.com/images/flags/4/tog.png"},{"Rank":91,"Name":"Haiti","TotalPoints":0.0,"PreviousPoints":501,"MovePosition":1,"FlagUrl":"http://img.fifa.com/images/flags/4/hai.png"},{"Rank":92,"Name":"Indonesia","TotalPoints":0.0,"PreviousPoints":505,"MovePosition":-1,"FlagUrl":"http://img.fifa.com/images/flags/4/idn.png"},{"Rank":93,"Name":"FYR Macedonia","TotalPoints":0.0,"PreviousPoints":497,"MovePosition":0,"FlagUrl":"http://img.fifa.com/images/flags/4/mkd.png"},{"Rank":94,"Name":"Iceland","TotalPoints":0.0,"PreviousPoints":494,"MovePosition":0,"FlagUrl":"http://img.fifa.com/images/flags/4/isl.png"},{"Rank":95,"Name":"Korea DPR","TotalPoints":0.0,"PreviousPoints":480,"MovePosition":2,"FlagUrl":"http://img.fifa.com/images/flags/4/prk.png"},{"Rank":96,"Name":"Turkmenistan","TotalPoints":0.0,"PreviousPoints":478,"MovePosition":3,"FlagUrl":"http://img.fifa.com/images/flags/4/tkm.png"},{"Rank":97,"Name":"Bolivia","TotalPoints":0.0,"PreviousPoints":484,"MovePosition":-2,"FlagUrl":"http://img.fifa.com/images/flags/4/bol.png"},{"Rank":98,"Name":"New Zealand","TotalPoints":0.0,"PreviousPoints":481,"MovePosition":-2,"FlagUrl":"http://img.fifa.com/images/flags/4/nzl.png"},{"Rank":99,"Name":"Rwanda","TotalPoints":0.0,"PreviousPoints":479,"MovePosition":-1,"FlagUrl":"http://img.fifa.com/images/flags/4/rwa.png"},{"Rank":100,"Name":"Lithuania","TotalPoints":0.0,"PreviousPoints":472,"MovePosition":0,"FlagUrl":"http://img.fifa.com/images/flags/4/ltu.png"},{"Rank":101,"Name":"Panama","TotalPoints":0.0,"PreviousPoints":469,"MovePosition":0,"FlagUrl":"http://img.fifa.com/images/flags/4/pan.png"},{"Rank":102,"Name":"Vietnam","TotalPoints":0.0,"PreviousPoints":465,"MovePosition":0,"FlagUrl":"http://img.fifa.com/images/flags/4/vie.png"},{"Rank":102,"Name":"Georgia","TotalPoints":0.0,"PreviousPoints":455,"MovePosition":4,"FlagUrl":"http://img.fifa.com/images/flags/4/geo.png"},{"Rank":104,"Name":"Singapore","TotalPoints":0.0,"PreviousPoints":460,"MovePosition":0,"FlagUrl":"http://img.fifa.com/images/flags/4/sin.png"},{"Rank":105,"Name":"Botswana","TotalPoints":0.0,"PreviousPoints":461,"MovePosition":-2,"FlagUrl":"http://img.fifa.com/images/flags/4/bot.png"},{"Rank":106,"Name":"Sudan","TotalPoints":0.0,"PreviousPoints":460,"MovePosition":-2,"FlagUrl":"http://img.fifa.com/images/flags/4/sdn.png"},{"Rank":107,"Name":"Gabon","TotalPoints":0.0,"PreviousPoints":438,"MovePosition":5,"FlagUrl":"http://img.fifa.com/images/flags/4/gab.png"},{"Rank":108,"Name":"Cyprus","TotalPoints":0.0,"PreviousPoints":442,"MovePosition":1,"FlagUrl":"http://img.fifa.com/images/flags/4/cyp.png"},{"Rank":108,"Name":"Lebanon","TotalPoints":0.0,"PreviousPoints":448,"MovePosition":-1,"FlagUrl":"http://img.fifa.com/images/flags/4/lib.png"},{"Rank":110,"Name":"El Salvador","TotalPoints":0.0,"PreviousPoints":446,"MovePosition":-2,"FlagUrl":"http://img.fifa.com/images/flags/4/slv.png"},{"Rank":111,"Name":"Northern Ireland","TotalPoints":0.0,"PreviousPoints":442,"MovePosition":-2,"FlagUrl":"http://img.fifa.com/images/flags/4/nir.png"},{"Rank":111,"Name":"Uganda","TotalPoints":0.0,"PreviousPoints":442,"MovePosition":-2,"FlagUrl":"http://img.fifa.com/images/flags/4/uga.png"},{"Rank":113,"Name":"Malawi","TotalPoints":0.0,"PreviousPoints":438,"MovePosition":-1,"FlagUrl":"http://img.fifa.com/images/flags/4/mwi.png"},{"Rank":114,"Name":"Malaysia","TotalPoints":0.0,"PreviousPoints":432,"MovePosition":0,"FlagUrl":"http://img.fifa.com/images/flags/4/mas.png"},{"Rank":115,"Name":"Moldova","TotalPoints":0.0,"PreviousPoints":428,"MovePosition":1,"FlagUrl":"http://img.fifa.com/images/flags/4/mda.png"},{"Rank":115,"Name":"Congo","TotalPoints":0.0,"PreviousPoints":420,"MovePosition":3,"FlagUrl":"http://img.fifa.com/images/flags/4/cgo.png"},{"Rank":117,"Name":"Azerbaijan","TotalPoints":0.0,"PreviousPoints":431,"MovePosition":-2,"FlagUrl":"http://img.fifa.com/images/flags/4/aze.png"},{"Rank":118,"Name":"St. Lucia","TotalPoints":0.0,"PreviousPoints":427,"MovePosition":-1,"FlagUrl":"http://img.fifa.com/images/flags/4/lca.png"},{"Rank":119,"Name":"St. Kitts and Nevis","TotalPoints":0.0,"PreviousPoints":416,"MovePosition":0,"FlagUrl":"http://img.fifa.com/images/flags/4/skn.png"},{"Rank":120,"Name":"Armenia","TotalPoints":0.0,"PreviousPoints":402,"MovePosition":0,"FlagUrl":"http://img.fifa.com/images/flags/4/arm.png"},{"Rank":121,"Name":"Barbados","TotalPoints":0.0,"PreviousPoints":392,"MovePosition":0,"FlagUrl":"http://img.fifa.com/images/flags/4/brb.png"},{"Rank":122,"Name":"Benin","TotalPoints":0.0,"PreviousPoints":391,"MovePosition":0,"FlagUrl":"http://img.fifa.com/images/flags/4/ben.png"},{"Rank":123,"Name":"Yemen","TotalPoints":0.0,"PreviousPoints":388,"MovePosition":0,"FlagUrl":"http://img.fifa.com/images/flags/4/yem.png"},{"Rank":124,"Name":"Liberia","TotalPoints":0.0,"PreviousPoints":384,"MovePosition":0,"FlagUrl":"http://img.fifa.com/images/flags/4/lbr.png"},{"Rank":125,"Name":"Tahiti","TotalPoints":0.0,"PreviousPoints":381,"MovePosition":0,"FlagUrl":"http://img.fifa.com/images/flags/4/tah.png"},{"Rank":126,"Name":"Mozambique","TotalPoints":0.0,"PreviousPoints":379,"MovePosition":0,"FlagUrl":"http://img.fifa.com/images/flags/4/moz.png"},{"Rank":126,"Name":"Palestine","TotalPoints":0.0,"PreviousPoints":379,"MovePosition":0,"FlagUrl":"http://img.fifa.com/images/flags/4/ple.png"},{"Rank":128,"Name":"Swaziland","TotalPoints":0.0,"PreviousPoints":378,"MovePosition":0,"FlagUrl":"http://img.fifa.com/images/flags/4/swz.png"},{"Rank":129,"Name":"Cape Verde Islands","TotalPoints":0.0,"PreviousPoints":376,"MovePosition":0,"FlagUrl":"http://img.fifa.com/images/flags/4/cpv.png"},{"Rank":130,"Name":"Solomon Islands","TotalPoints":0.0,"PreviousPoints":374,"MovePosition":0,"FlagUrl":"http://img.fifa.com/images/flags/4/sol.png"},{"Rank":131,"Name":"Ethiopia","TotalPoints":0.0,"PreviousPoints":368,"MovePosition":0,"FlagUrl":"http://img.fifa.com/images/flags/4/eth.png"},{"Rank":132,"Name":"Faroe Islands","TotalPoints":0.0,"PreviousPoints":367,"MovePosition":0,"FlagUrl":"http://img.fifa.com/images/flags/4/fro.png"},{"Rank":133,"Name":"India","TotalPoints":0.0,"PreviousPoints":365,"MovePosition":0,"FlagUrl":"http://img.fifa.com/images/flags/4/ind.png"},{"Rank":134,"Name":"Hong Kong","TotalPoints":0.0,"PreviousPoints":361,"MovePosition":0,"FlagUrl":"http://img.fifa.com/images/flags/4/hkg.png"},{"Rank":135,"Name":"St. Vincent and the Grenadines","TotalPoints":0.0,"PreviousPoints":346,"MovePosition":3,"FlagUrl":"http://img.fifa.com/images/flags/4/vin.png"},{"Rank":136,"Name":"Malta","TotalPoints":0.0,"PreviousPoints":354,"MovePosition":-1,"FlagUrl":"http://img.fifa.com/images/flags/4/mlt.png"},{"Rank":136,"Name":"Tajikistan","TotalPoints":0.0,"PreviousPoints":354,"MovePosition":-1,"FlagUrl":"http://img.fifa.com/images/flags/4/tjk.png"},{"Rank":138,"Name":"Fiji","TotalPoints":0.0,"PreviousPoints":353,"MovePosition":-1,"FlagUrl":"http://img.fifa.com/images/flags/4/fij.png"},{"Rank":139,"Name":"Andorra","TotalPoints":0.0,"PreviousPoints":335,"MovePosition":2,"FlagUrl":"http://img.fifa.com/images/flags/4/and.png"},{"Rank":140,"Name":"Sri Lanka","TotalPoints":0.0,"PreviousPoints":345,"MovePosition":-1,"FlagUrl":"http://img.fifa.com/images/flags/4/sri.png"},{"Rank":141,"Name":"Maldives","TotalPoints":0.0,"PreviousPoints":337,"MovePosition":-1,"FlagUrl":"http://img.fifa.com/images/flags/4/mdv.png"},{"Rank":142,"Name":"Lesotho","TotalPoints":0.0,"PreviousPoints":335,"MovePosition":-1,"FlagUrl":"http://img.fifa.com/images/flags/4/les.png"},{"Rank":143,"Name":"Mauritius","TotalPoints":0.0,"PreviousPoints":333,"MovePosition":0,"FlagUrl":"http://img.fifa.com/images/flags/4/mri.png"},{"Rank":144,"Name":"Liechtenstein","TotalPoints":0.0,"PreviousPoints":330,"MovePosition":0,"FlagUrl":"http://img.fifa.com/images/flags/4/lie.png"},{"Rank":145,"Name":"Burundi","TotalPoints":0.0,"PreviousPoints":325,"MovePosition":0,"FlagUrl":"http://img.fifa.com/images/flags/4/bdi.png"},{"Rank":145,"Name":"Vanuatu","TotalPoints":0.0,"PreviousPoints":325,"MovePosition":0,"FlagUrl":"http://img.fifa.com/images/flags/4/van.png"},{"Rank":147,"Name":"Myanmar","TotalPoints":0.0,"PreviousPoints":321,"MovePosition":0,"FlagUrl":"http://img.fifa.com/images/flags/4/mya.png"},{"Rank":148,"Name":"Grenada","TotalPoints":0.0,"PreviousPoints":319,"MovePosition":0,"FlagUrl":"http://img.fifa.com/images/flags/4/grn.png"},{"Rank":149,"Name":"Kazakhstan","TotalPoints":0.0,"PreviousPoints":313,"MovePosition":0,"FlagUrl":"http://img.fifa.com/images/flags/4/kaz.png"},{"Rank":150,"Name":"Madagascar","TotalPoints":0.0,"PreviousPoints":312,"MovePosition":0,"FlagUrl":"http://img.fifa.com/images/flags/4/mad.png"},{"Rank":151,"Name":"Suriname","TotalPoints":0.0,"PreviousPoints":302,"MovePosition":0,"FlagUrl":"http://img.fifa.com/images/flags/4/sur.png"},{"Rank":152,"Name":"Kyrgyzstan","TotalPoints":0.0,"PreviousPoints":293,"MovePosition":0,"FlagUrl":"http://img.fifa.com/images/flags/4/kgz.png"},{"Rank":153,"Name":"Antigua and Barbuda","TotalPoints":0.0,"PreviousPoints":262,"MovePosition":0,"FlagUrl":"http://img.fifa.com/images/flags/4/atg.png"},{"Rank":154,"Name":"Gambia","TotalPoints":0.0,"PreviousPoints":260,"MovePosition":0,"FlagUrl":"http://img.fifa.com/images/flags/4/gam.png"},{"Rank":154,"Name":"Luxembourg","TotalPoints":0.0,"PreviousPoints":259,"MovePosition":1,"FlagUrl":"http://img.fifa.com/images/flags/4/lux.png"},{"Rank":156,"Name":"Bermuda","TotalPoints":0.0,"PreviousPoints":257,"MovePosition":1,"FlagUrl":"http://img.fifa.com/images/flags/4/ber.png"},{"Rank":156,"Name":"Chinese Taipei","TotalPoints":0.0,"PreviousPoints":259,"MovePosition":-1,"FlagUrl":"http://img.fifa.com/images/flags/4/tpe.png"},{"Rank":158,"Name":"Namibia","TotalPoints":0.0,"PreviousPoints":239,"MovePosition":0,"FlagUrl":"http://img.fifa.com/images/flags/4/nam.png"},{"Rank":158,"Name":"Nicaragua","TotalPoints":0.0,"PreviousPoints":239,"MovePosition":0,"FlagUrl":"http://img.fifa.com/images/flags/4/nca.png"},{"Rank":160,"Name":"Chad","TotalPoints":0.0,"PreviousPoints":212,"MovePosition":8,"FlagUrl":"http://img.fifa.com/images/flags/4/cha.png"},{"Rank":161,"Name":"San Marino","TotalPoints":0.0,"PreviousPoints":221,"MovePosition":4,"FlagUrl":"http://img.fifa.com/images/flags/4/smr.png"},{"Rank":162,"Name":"Sierra Leone","TotalPoints":0.0,"PreviousPoints":232,"MovePosition":-2,"FlagUrl":"http://img.fifa.com/images/flags/4/sle.png"},{"Rank":163,"Name":"Papua New Guinea","TotalPoints":0.0,"PreviousPoints":231,"MovePosition":-2,"FlagUrl":"http://img.fifa.com/images/flags/4/png.png"},{"Rank":164,"Name":"Laos","TotalPoints":0.0,"PreviousPoints":228,"MovePosition":-2,"FlagUrl":"http://img.fifa.com/images/flags/4/lao.png"},{"Rank":165,"Name":"British Virgin Islands","TotalPoints":0.0,"PreviousPoints":222,"MovePosition":-2,"FlagUrl":"http://img.fifa.com/images/flags/4/vgb.png"},{"Rank":166,"Name":"Netherlands Antilles","TotalPoints":0.0,"PreviousPoints":222,"MovePosition":-3,"FlagUrl":"http://img.fifa.com/images/flags/4/ant.png"},{"Rank":167,"Name":"Dominica","TotalPoints":0.0,"PreviousPoints":218,"MovePosition":-1,"FlagUrl":"http://img.fifa.com/images/flags/4/dma.png"},{"Rank":168,"Name":"Bangladesh","TotalPoints":0.0,"PreviousPoints":217,"MovePosition":-1,"FlagUrl":"http://img.fifa.com/images/flags/4/ban.png"},{"Rank":169,"Name":"Eritrea","TotalPoints":0.0,"PreviousPoints":206,"MovePosition":0,"FlagUrl":"http://img.fifa.com/images/flags/4/eri.png"},{"Rank":170,"Name":"Equatorial Guinea","TotalPoints":0.0,"PreviousPoints":193,"MovePosition":1,"FlagUrl":"http://img.fifa.com/images/flags/4/eqg.png"},{"Rank":171,"Name":"Dominican Republic","TotalPoints":0.0,"PreviousPoints":195,"MovePosition":-1,"FlagUrl":"http://img.fifa.com/images/flags/4/dom.png"},{"Rank":172,"Name":"Tanzania","TotalPoints":0.0,"PreviousPoints":187,"MovePosition":0,"FlagUrl":"http://img.fifa.com/images/flags/4/tan.png"},{"Rank":173,"Name":"Seychelles","TotalPoints":0.0,"PreviousPoints":177,"MovePosition":0,"FlagUrl":"http://img.fifa.com/images/flags/4/sey.png"},{"Rank":174,"Name":"Niger","TotalPoints":0.0,"PreviousPoints":177,"MovePosition":-1,"FlagUrl":"http://img.fifa.com/images/flags/4/nig.png"},{"Rank":175,"Name":"Mauritania","TotalPoints":0.0,"PreviousPoints":172,"MovePosition":0,"FlagUrl":"http://img.fifa.com/images/flags/4/mtn.png"},{"Rank":176,"Name":"Cayman Islands","TotalPoints":0.0,"PreviousPoints":168,"MovePosition":0,"FlagUrl":"http://img.fifa.com/images/flags/4/cay.png"},{"Rank":177,"Name":"Nepal","TotalPoints":0.0,"PreviousPoints":168,"MovePosition":-1,"FlagUrl":"http://img.fifa.com/images/flags/4/nep.png"},{"Rank":177,"Name":"Pakistan","TotalPoints":0.0,"PreviousPoints":168,"MovePosition":-1,"FlagUrl":"http://img.fifa.com/images/flags/4/pak.png"},{"Rank":177,"Name":"Samoa","TotalPoints":0.0,"PreviousPoints":167,"MovePosition":2,"FlagUrl":"http://img.fifa.com/images/flags/4/sam.png"},{"Rank":180,"Name":"Central African Republic","TotalPoints":0.0,"PreviousPoints":150,"MovePosition":0,"FlagUrl":"http://img.fifa.com/images/flags/4/cta.png"},{"Rank":181,"Name":"Belize","TotalPoints":0.0,"PreviousPoints":147,"MovePosition":0,"FlagUrl":"http://img.fifa.com/images/flags/4/blz.png"},{"Rank":182,"Name":"Guyana","TotalPoints":0.0,"PreviousPoints":145,"MovePosition":0,"FlagUrl":"http://img.fifa.com/images/flags/4/guy.png"},{"Rank":183,"Name":"Tonga","TotalPoints":0.0,"PreviousPoints":138,"MovePosition":0,"FlagUrl":"http://img.fifa.com/images/flags/4/tga.png"},{"Rank":184,"Name":"Cambodia","TotalPoints":0.0,"PreviousPoints":126,"MovePosition":0,"FlagUrl":"http://img.fifa.com/images/flags/4/cam.png"},{"Rank":185,"Name":"Mongolia","TotalPoints":0.0,"PreviousPoints":120,"MovePosition":0,"FlagUrl":"http://img.fifa.com/images/flags/4/mng.png"},{"Rank":186,"Name":"New Caledonia","TotalPoints":0.0,"PreviousPoints":119,"MovePosition":0,"FlagUrl":"http://img.fifa.com/images/flags/4/ncl.png"},{"Rank":187,"Name":"Philippines","TotalPoints":0.0,"PreviousPoints":101,"MovePosition":0,"FlagUrl":"http://img.fifa.com/images/flags/4/phi.png"},{"Rank":188,"Name":"Bhutan","TotalPoints":0.0,"PreviousPoints":97,"MovePosition":0,"FlagUrl":"http://img.fifa.com/images/flags/4/bhu.png"},{"Rank":189,"Name":"Somalia","TotalPoints":0.0,"PreviousPoints":95,"MovePosition":0,"FlagUrl":"http://img.fifa.com/images/flags/4/som.png"},{"Rank":190,"Name":"Macau","TotalPoints":0.0,"PreviousPoints":92,"MovePosition":0,"FlagUrl":"http://img.fifa.com/images/flags/4/mac.png"},{"Rank":191,"Name":"Cook Islands","TotalPoints":0.0,"PreviousPoints":91,"MovePosition":0,"FlagUrl":"http://img.fifa.com/images/flags/4/cok.png"},{"Rank":191,"Name":"Guinea-Bissau","TotalPoints":0.0,"PreviousPoints":91,"MovePosition":0,"FlagUrl":"http://img.fifa.com/images/flags/4/gnb.png"},{"Rank":193,"Name":"Bahamas","TotalPoints":0.0,"PreviousPoints":90,"MovePosition":0,"FlagUrl":"http://img.fifa.com/images/flags/4/bah.png"},{"Rank":194,"Name":"Puerto Rico","TotalPoints":0.0,"PreviousPoints":75,"MovePosition":0,"FlagUrl":"http://img.fifa.com/images/flags/4/pur.png"},{"Rank":195,"Name":"São Tomé e Príncipe","TotalPoints":0.0,"PreviousPoints":74,"MovePosition":0,"FlagUrl":"http://img.fifa.com/images/flags/4/stp.png"},{"Rank":196,"Name":"US Virgin Islands","TotalPoints":0.0,"PreviousPoints":70,"MovePosition":0,"FlagUrl":"http://img.fifa.com/images/flags/4/vir.png"},{"Rank":197,"Name":"Anguilla","TotalPoints":0.0,"PreviousPoints":65,"MovePosition":0,"FlagUrl":"http://img.fifa.com/images/flags/4/aia.png"},{"Rank":198,"Name":"Aruba","TotalPoints":0.0,"PreviousPoints":64,"MovePosition":0,"FlagUrl":"http://img.fifa.com/images/flags/4/aru.png"},{"Rank":199,"Name":"Brunei Darussalam","TotalPoints":0.0,"PreviousPoints":63,"MovePosition":0,"FlagUrl":"http://img.fifa.com/images/flags/4/bru.png"},{"Rank":200,"Name":"Afghanistan","TotalPoints":0.0,"PreviousPoints":57,"MovePosition":0,"FlagUrl":"http://img.fifa.com/images/flags/4/afg.png"},{"Rank":201,"Name":"Djibouti","TotalPoints":0.0,"PreviousPoints":42,"MovePosition":0,"FlagUrl":"http://img.fifa.com/images/flags/4/dji.png"},{"Rank":202,"Name":"Montserrat","TotalPoints":0.0,"PreviousPoints":36,"MovePosition":0,"FlagUrl":"http://img.fifa.com/images/flags/4/msr.png"},{"Rank":203,"Name":"Turks and Caicos Islands","TotalPoints":0.0,"PreviousPoints":28,"MovePosition":0,"FlagUrl":"http://img.fifa.com/images/flags/4/tca.png"},{"Rank":204,"Name":"American Samoa","TotalPoints":0.0,"PreviousPoints":19,"MovePosition":0,"FlagUrl":"http://img.fifa.com/images/flags/4/asa.png"},{"Rank":205,"Name":"Guam","TotalPoints":0.0,"PreviousPoints":15,"MovePosition":0,"FlagUrl":"http://img.fifa.com/images/flags/4/gum.png"}],"Id":129,"Date":"2005-02-16T00:00:00"}