{"Teams":[{"Rank":1,"Name":"Spain","TotalPoints":1563.83,"PreviousPoints":1564,"MovePosition":0,"FlagUrl":"http://img.fifa.com/images/flags/4/esp.png"},{"Rank":2,"Name":"Netherlands","TotalPoints":1365.43,"PreviousPoints":1365,"MovePosition":0,"FlagUrl":"http://img.fifa.com/images/flags/4/ned.png"},{"Rank":3,"Name":"Germany","TotalPoints":1345.21,"PreviousPoints":1345,"MovePosition":0,"FlagUrl":"http://img.fifa.com/images/flags/4/ger.png"},{"Rank":4,"Name":"Uruguay","TotalPoints":1309.23,"PreviousPoints":1309,"MovePosition":0,"FlagUrl":"http://img.fifa.com/images/flags/4/uru.png"},{"Rank":5,"Name":"England","TotalPoints":1173.37,"PreviousPoints":1173,"MovePosition":0,"FlagUrl":"http://img.fifa.com/images/flags/4/eng.png"},{"Rank":6,"Name":"Brazil","TotalPoints":1142.6,"PreviousPoints":1143,"MovePosition":0,"FlagUrl":"http://img.fifa.com/images/flags/4/bra.png"},{"Rank":7,"Name":"Portugal","TotalPoints":1100.38,"PreviousPoints":1100,"MovePosition":0,"FlagUrl":"http://img.fifa.com/images/flags/4/por.png"},{"Rank":8,"Name":"Croatia","TotalPoints":1091.15,"PreviousPoints":1091,"MovePosition":0,"FlagUrl":"http://img.fifa.com/images/flags/4/cro.png"},{"Rank":9,"Name":"Italy","TotalPoints":1082.35,"PreviousPoints":1082,"MovePosition":0,"FlagUrl":"http://img.fifa.com/images/flags/4/ita.png"},{"Rank":10,"Name":"Argentina","TotalPoints":1067.03,"PreviousPoints":1067,"MovePosition":0,"FlagUrl":"http://img.fifa.com/images/flags/4/arg.png"},{"Rank":11,"Name":"Denmark","TotalPoints":1035.14,"PreviousPoints":1035,"MovePosition":0,"FlagUrl":"http://img.fifa.com/images/flags/4/den.png"},{"Rank":12,"Name":"Russia","TotalPoints":970.7,"PreviousPoints":971,"MovePosition":0,"FlagUrl":"http://img.fifa.com/images/flags/4/rus.png"},{"Rank":13,"Name":"Chile","TotalPoints":970.35,"PreviousPoints":970,"MovePosition":0,"FlagUrl":"http://img.fifa.com/images/flags/4/chi.png"},{"Rank":14,"Name":"Greece","TotalPoints":963.61,"PreviousPoints":964,"MovePosition":0,"FlagUrl":"http://img.fifa.com/images/flags/4/gre.png"},{"Rank":15,"Name":"France","TotalPoints":914.52,"PreviousPoints":915,"MovePosition":0,"FlagUrl":"http://img.fifa.com/images/flags/4/fra.png"},{"Rank":16,"Name":"Côte d'Ivoire","TotalPoints":911.87,"PreviousPoints":912,"MovePosition":0,"FlagUrl":"http://img.fifa.com/images/flags/4/civ.png"},{"Rank":17,"Name":"Switzerland","TotalPoints":897.84,"PreviousPoints":898,"MovePosition":0,"FlagUrl":"http://img.fifa.com/images/flags/4/sui.png"},{"Rank":18,"Name":"Sweden","TotalPoints":891.16,"PreviousPoints":891,"MovePosition":0,"FlagUrl":"http://img.fifa.com/images/flags/4/swe.png"},{"Rank":19,"Name":"Japan","TotalPoints":884.18,"PreviousPoints":884,"MovePosition":0,"FlagUrl":"http://img.fifa.com/images/flags/4/jpn.png"},{"Rank":20,"Name":"Bosnia and Herzegovina","TotalPoints":868.57,"PreviousPoints":838,"MovePosition":3,"FlagUrl":"http://img.fifa.com/images/flags/4/bih.png"},{"Rank":21,"Name":"Mexico","TotalPoints":866.49,"PreviousPoints":866,"MovePosition":-1,"FlagUrl":"http://img.fifa.com/images/flags/4/mex.png"},{"Rank":22,"Name":"Republic of Ireland","TotalPoints":863.85,"PreviousPoints":864,"MovePosition":-1,"FlagUrl":"http://img.fifa.com/images/flags/4/irl.png"},{"Rank":23,"Name":"Australia","TotalPoints":850.78,"PreviousPoints":851,"MovePosition":-1,"FlagUrl":"http://img.fifa.com/images/flags/4/aus.png"},{"Rank":24,"Name":"Paraguay","TotalPoints":794.66,"PreviousPoints":795,"MovePosition":0,"FlagUrl":"http://img.fifa.com/images/flags/4/par.png"},{"Rank":25,"Name":"Norway","TotalPoints":788.29,"PreviousPoints":788,"MovePosition":0,"FlagUrl":"http://img.fifa.com/images/flags/4/nor.png"},{"Rank":26,"Name":"Slovenia","TotalPoints":779.5,"PreviousPoints":780,"MovePosition":0,"FlagUrl":"http://img.fifa.com/images/flags/4/svn.png"},{"Rank":27,"Name":"Serbia","TotalPoints":775.06,"PreviousPoints":775,"MovePosition":0,"FlagUrl":"http://img.fifa.com/images/flags/4/srb.png"},{"Rank":28,"Name":"Turkey","TotalPoints":768.93,"PreviousPoints":769,"MovePosition":0,"FlagUrl":"http://img.fifa.com/images/flags/4/tur.png"},{"Rank":29,"Name":"Ghana","TotalPoints":760.55,"PreviousPoints":761,"MovePosition":0,"FlagUrl":"http://img.fifa.com/images/flags/4/gha.png"},{"Rank":30,"Name":"Algeria","TotalPoints":757.94,"PreviousPoints":758,"MovePosition":0,"FlagUrl":"http://img.fifa.com/images/flags/4/alg.png"},{"Rank":31,"Name":"Egypt","TotalPoints":755.22,"PreviousPoints":757,"MovePosition":0,"FlagUrl":"http://img.fifa.com/images/flags/4/egy.png"},{"Rank":32,"Name":"Korea Republic","TotalPoints":752.49,"PreviousPoints":752,"MovePosition":0,"FlagUrl":"http://img.fifa.com/images/flags/4/kor.png"},{"Rank":33,"Name":"Czech Republic","TotalPoints":749.02,"PreviousPoints":749,"MovePosition":0,"FlagUrl":"http://img.fifa.com/images/flags/4/cze.png"},{"Rank":34,"Name":"USA","TotalPoints":720.85,"PreviousPoints":721,"MovePosition":0,"FlagUrl":"http://img.fifa.com/images/flags/4/usa.png"},{"Rank":35,"Name":"Peru","TotalPoints":711.61,"PreviousPoints":712,"MovePosition":0,"FlagUrl":"http://img.fifa.com/images/flags/4/per.png"},{"Rank":36,"Name":"Colombia","TotalPoints":709.19,"PreviousPoints":709,"MovePosition":0,"FlagUrl":"http://img.fifa.com/images/flags/4/col.png"},{"Rank":37,"Name":"Hungary","TotalPoints":665.37,"PreviousPoints":665,"MovePosition":0,"FlagUrl":"http://img.fifa.com/images/flags/4/hun.png"},{"Rank":37,"Name":"Israel","TotalPoints":665.19,"PreviousPoints":665,"MovePosition":0,"FlagUrl":"http://img.fifa.com/images/flags/4/isr.png"},{"Rank":39,"Name":"Venezuela","TotalPoints":661.13,"PreviousPoints":661,"MovePosition":0,"FlagUrl":"http://img.fifa.com/images/flags/4/ven.png"},{"Rank":40,"Name":"Slovakia","TotalPoints":648.47,"PreviousPoints":648,"MovePosition":0,"FlagUrl":"http://img.fifa.com/images/flags/4/svk.png"},{"Rank":41,"Name":"Belgium","TotalPoints":646.84,"PreviousPoints":647,"MovePosition":0,"FlagUrl":"http://img.fifa.com/images/flags/4/bel.png"},{"Rank":42,"Name":"Ecuador","TotalPoints":633.97,"PreviousPoints":630,"MovePosition":0,"FlagUrl":"http://img.fifa.com/images/flags/4/ecu.png"},{"Rank":43,"Name":"Nigeria","TotalPoints":627.48,"PreviousPoints":627,"MovePosition":0,"FlagUrl":"http://img.fifa.com/images/flags/4/nga.png"},{"Rank":44,"Name":"Senegal","TotalPoints":624.65,"PreviousPoints":625,"MovePosition":0,"FlagUrl":"http://img.fifa.com/images/flags/4/sen.png"},{"Rank":45,"Name":"Iran","TotalPoints":615.55,"PreviousPoints":616,"MovePosition":0,"FlagUrl":"http://img.fifa.com/images/flags/4/irn.png"},{"Rank":46,"Name":"Armenia","TotalPoints":612.06,"PreviousPoints":612,"MovePosition":0,"FlagUrl":"http://img.fifa.com/images/flags/4/arm.png"},{"Rank":47,"Name":"Scotland","TotalPoints":599.48,"PreviousPoints":599,"MovePosition":2,"FlagUrl":"http://img.fifa.com/images/flags/4/sco.png"},{"Rank":48,"Name":"Wales","TotalPoints":590.66,"PreviousPoints":591,"MovePosition":2,"FlagUrl":"http://img.fifa.com/images/flags/4/wal.png"},{"Rank":49,"Name":"Panama","TotalPoints":589.43,"PreviousPoints":585,"MovePosition":2,"FlagUrl":"http://img.fifa.com/images/flags/4/pan.png"},{"Rank":50,"Name":"Cameroon","TotalPoints":587.87,"PreviousPoints":602,"MovePosition":-2,"FlagUrl":"http://img.fifa.com/images/flags/4/cmr.png"},{"Rank":51,"Name":"Montenegro","TotalPoints":585.48,"PreviousPoints":585,"MovePosition":0,"FlagUrl":"http://img.fifa.com/images/flags/4/mne.png"},{"Rank":52,"Name":"South Africa","TotalPoints":577.35,"PreviousPoints":577,"MovePosition":1,"FlagUrl":"http://img.fifa.com/images/flags/4/rsa.png"},{"Rank":53,"Name":"Honduras","TotalPoints":573.85,"PreviousPoints":570,"MovePosition":1,"FlagUrl":"http://img.fifa.com/images/flags/4/hon.png"},{"Rank":54,"Name":"Jamaica","TotalPoints":572.71,"PreviousPoints":609,"MovePosition":-7,"FlagUrl":"http://img.fifa.com/images/flags/4/jam.png"},{"Rank":55,"Name":"Ukraine","TotalPoints":568.05,"PreviousPoints":568,"MovePosition":0,"FlagUrl":"http://img.fifa.com/images/flags/4/ukr.png"},{"Rank":56,"Name":"Romania","TotalPoints":562.13,"PreviousPoints":562,"MovePosition":0,"FlagUrl":"http://img.fifa.com/images/flags/4/rou.png"},{"Rank":57,"Name":"Estonia","TotalPoints":555.09,"PreviousPoints":543,"MovePosition":1,"FlagUrl":"http://img.fifa.com/images/flags/4/est.png"},{"Rank":58,"Name":"Cape Verde Islands","TotalPoints":549.02,"PreviousPoints":544,"MovePosition":-1,"FlagUrl":"http://img.fifa.com/images/flags/4/cpv.png"},{"Rank":59,"Name":"Tunisia","TotalPoints":537.18,"PreviousPoints":537,"MovePosition":0,"FlagUrl":"http://img.fifa.com/images/flags/4/tun.png"},{"Rank":60,"Name":"Sierra Leone","TotalPoints":526.16,"PreviousPoints":521,"MovePosition":1,"FlagUrl":"http://img.fifa.com/images/flags/4/sle.png"},{"Rank":61,"Name":"Morocco","TotalPoints":523.71,"PreviousPoints":524,"MovePosition":-1,"FlagUrl":"http://img.fifa.com/images/flags/4/mar.png"},{"Rank":62,"Name":"Burkina Faso","TotalPoints":517.54,"PreviousPoints":518,"MovePosition":0,"FlagUrl":"http://img.fifa.com/images/flags/4/bfa.png"},{"Rank":63,"Name":"Libya","TotalPoints":514.28,"PreviousPoints":514,"MovePosition":0,"FlagUrl":"http://img.fifa.com/images/flags/4/lby.png"},{"Rank":64,"Name":"Belarus","TotalPoints":501.43,"PreviousPoints":501,"MovePosition":1,"FlagUrl":"http://img.fifa.com/images/flags/4/blr.png"},{"Rank":65,"Name":"Costa Rica","TotalPoints":495.23,"PreviousPoints":503,"MovePosition":-1,"FlagUrl":"http://img.fifa.com/images/flags/4/crc.png"},{"Rank":66,"Name":"Poland","TotalPoints":491.67,"PreviousPoints":487,"MovePosition":0,"FlagUrl":"http://img.fifa.com/images/flags/4/pol.png"},{"Rank":67,"Name":"Mali","TotalPoints":471.72,"PreviousPoints":472,"MovePosition":0,"FlagUrl":"http://img.fifa.com/images/flags/4/mli.png"},{"Rank":68,"Name":"Latvia","TotalPoints":466.2,"PreviousPoints":466,"MovePosition":0,"FlagUrl":"http://img.fifa.com/images/flags/4/lva.png"},{"Rank":69,"Name":"El Salvador","TotalPoints":462.54,"PreviousPoints":463,"MovePosition":0,"FlagUrl":"http://img.fifa.com/images/flags/4/slv.png"},{"Rank":70,"Name":"Austria","TotalPoints":458.55,"PreviousPoints":459,"MovePosition":1,"FlagUrl":"http://img.fifa.com/images/flags/4/aut.png"},{"Rank":71,"Name":"China PR","TotalPoints":457.18,"PreviousPoints":455,"MovePosition":1,"FlagUrl":"http://img.fifa.com/images/flags/4/chn.png"},{"Rank":72,"Name":"Canada","TotalPoints":454.8,"PreviousPoints":455,"MovePosition":0,"FlagUrl":"http://img.fifa.com/images/flags/4/can.png"},{"Rank":73,"Name":"Georgia","TotalPoints":451.44,"PreviousPoints":451,"MovePosition":1,"FlagUrl":"http://img.fifa.com/images/flags/4/geo.png"},{"Rank":74,"Name":"Albania","TotalPoints":449.94,"PreviousPoints":450,"MovePosition":1,"FlagUrl":"http://img.fifa.com/images/flags/4/alb.png"},{"Rank":75,"Name":"Uzbekistan","TotalPoints":449.46,"PreviousPoints":449,"MovePosition":1,"FlagUrl":"http://img.fifa.com/images/flags/4/uzb.png"},{"Rank":76,"Name":"Trinidad and Tobago","TotalPoints":447.49,"PreviousPoints":409,"MovePosition":10,"FlagUrl":"http://img.fifa.com/images/flags/4/tri.png"},{"Rank":77,"Name":"Gabon","TotalPoints":445.16,"PreviousPoints":445,"MovePosition":0,"FlagUrl":"http://img.fifa.com/images/flags/4/gab.png"},{"Rank":78,"Name":"Iraq","TotalPoints":440.46,"PreviousPoints":429,"MovePosition":3,"FlagUrl":"http://img.fifa.com/images/flags/4/irq.png"},{"Rank":79,"Name":"Zambia","TotalPoints":439.1,"PreviousPoints":436,"MovePosition":0,"FlagUrl":"http://img.fifa.com/images/flags/4/zam.png"},{"Rank":80,"Name":"Guinea","TotalPoints":435.66,"PreviousPoints":436,"MovePosition":-1,"FlagUrl":"http://img.fifa.com/images/flags/4/gui.png"},{"Rank":81,"Name":"Haiti","TotalPoints":428.91,"PreviousPoints":438,"MovePosition":-3,"FlagUrl":"http://img.fifa.com/images/flags/4/hai.png"},{"Rank":82,"Name":"Jordan","TotalPoints":417.21,"PreviousPoints":419,"MovePosition":0,"FlagUrl":"http://img.fifa.com/images/flags/4/jor.png"},{"Rank":83,"Name":"Angola","TotalPoints":411.96,"PreviousPoints":412,"MovePosition":1,"FlagUrl":"http://img.fifa.com/images/flags/4/ang.png"},{"Rank":84,"Name":"Bulgaria","TotalPoints":409.78,"PreviousPoints":410,"MovePosition":1,"FlagUrl":"http://img.fifa.com/images/flags/4/bul.png"},{"Rank":85,"Name":"Oman","TotalPoints":408.37,"PreviousPoints":387,"MovePosition":8,"FlagUrl":"http://img.fifa.com/images/flags/4/oma.png"},{"Rank":86,"Name":"Finland","TotalPoints":405.44,"PreviousPoints":405,"MovePosition":2,"FlagUrl":"http://img.fifa.com/images/flags/4/fin.png"},{"Rank":87,"Name":"Antigua and Barbuda","TotalPoints":404.11,"PreviousPoints":418,"MovePosition":-4,"FlagUrl":"http://img.fifa.com/images/flags/4/atg.png"},{"Rank":88,"Name":"Northern Ireland","TotalPoints":402.93,"PreviousPoints":403,"MovePosition":1,"FlagUrl":"http://img.fifa.com/images/flags/4/nir.png"},{"Rank":89,"Name":"Uganda","TotalPoints":397.81,"PreviousPoints":394,"MovePosition":2,"FlagUrl":"http://img.fifa.com/images/flags/4/uga.png"},{"Rank":90,"Name":"Guatemala","TotalPoints":397.14,"PreviousPoints":397,"MovePosition":0,"FlagUrl":"http://img.fifa.com/images/flags/4/gua.png"},{"Rank":91,"Name":"Guyana","TotalPoints":386.68,"PreviousPoints":370,"MovePosition":6,"FlagUrl":"http://img.fifa.com/images/flags/4/guy.png"},{"Rank":92,"Name":"Lithuania","TotalPoints":382.09,"PreviousPoints":382,"MovePosition":2,"FlagUrl":"http://img.fifa.com/images/flags/4/ltu.png"},{"Rank":93,"Name":"Qatar","TotalPoints":377.71,"PreviousPoints":375,"MovePosition":2,"FlagUrl":"http://img.fifa.com/images/flags/4/qat.png"},{"Rank":94,"Name":"Malawi","TotalPoints":373.85,"PreviousPoints":407,"MovePosition":-7,"FlagUrl":"http://img.fifa.com/images/flags/4/mwi.png"},{"Rank":95,"Name":"Botswana","TotalPoints":371.1,"PreviousPoints":371,"MovePosition":1,"FlagUrl":"http://img.fifa.com/images/flags/4/bot.png"},{"Rank":96,"Name":"Saudi Arabia","TotalPoints":363.11,"PreviousPoints":361,"MovePosition":2,"FlagUrl":"http://img.fifa.com/images/flags/4/ksa.png"},{"Rank":97,"Name":"Niger","TotalPoints":361.49,"PreviousPoints":361,"MovePosition":1,"FlagUrl":"http://img.fifa.com/images/flags/4/nig.png"},{"Rank":98,"Name":"Zimbabwe","TotalPoints":354.44,"PreviousPoints":462,"MovePosition":-28,"FlagUrl":"http://img.fifa.com/images/flags/4/zim.png"},{"Rank":99,"Name":"Kuwait","TotalPoints":351.01,"PreviousPoints":351,"MovePosition":1,"FlagUrl":"http://img.fifa.com/images/flags/4/kuw.png"},{"Rank":99,"Name":"Vietnam","TotalPoints":350.63,"PreviousPoints":234,"MovePosition":35,"FlagUrl":"http://img.fifa.com/images/flags/4/vie.png"},{"Rank":101,"Name":"Bahrain","TotalPoints":350.14,"PreviousPoints":340,"MovePosition":1,"FlagUrl":"http://img.fifa.com/images/flags/4/bhr.png"},{"Rank":101,"Name":"Togo","TotalPoints":350.37,"PreviousPoints":350,"MovePosition":0,"FlagUrl":"http://img.fifa.com/images/flags/4/tog.png"},{"Rank":103,"Name":"FYR Macedonia","TotalPoints":333.36,"PreviousPoints":333,"MovePosition":0,"FlagUrl":"http://img.fifa.com/images/flags/4/mkd.png"},{"Rank":104,"Name":"Iceland","TotalPoints":325.44,"PreviousPoints":325,"MovePosition":0,"FlagUrl":"http://img.fifa.com/images/flags/4/isl.png"},{"Rank":105,"Name":"Mozambique","TotalPoints":321.66,"PreviousPoints":324,"MovePosition":0,"FlagUrl":"http://img.fifa.com/images/flags/4/moz.png"},{"Rank":106,"Name":"Rwanda","TotalPoints":314.05,"PreviousPoints":297,"MovePosition":8,"FlagUrl":"http://img.fifa.com/images/flags/4/rwa.png"},{"Rank":107,"Name":"Bermuda","TotalPoints":310.29,"PreviousPoints":307,"MovePosition":2,"FlagUrl":"http://img.fifa.com/images/flags/4/ber.png"},{"Rank":108,"Name":"Bolivia","TotalPoints":309.09,"PreviousPoints":309,"MovePosition":-2,"FlagUrl":"http://img.fifa.com/images/flags/4/bol.png"},{"Rank":108,"Name":"Puerto Rico","TotalPoints":308.91,"PreviousPoints":309,"MovePosition":-2,"FlagUrl":"http://img.fifa.com/images/flags/4/pur.png"},{"Rank":110,"Name":"Korea DPR","TotalPoints":305.97,"PreviousPoints":306,"MovePosition":0,"FlagUrl":"http://img.fifa.com/images/flags/4/prk.png"},{"Rank":111,"Name":"Lebanon","TotalPoints":305.36,"PreviousPoints":305,"MovePosition":0,"FlagUrl":"http://img.fifa.com/images/flags/4/lib.png"},{"Rank":112,"Name":"Azerbaijan","TotalPoints":299.65,"PreviousPoints":300,"MovePosition":1,"FlagUrl":"http://img.fifa.com/images/flags/4/aze.png"},{"Rank":113,"Name":"Sudan","TotalPoints":297.13,"PreviousPoints":304,"MovePosition":-1,"FlagUrl":"http://img.fifa.com/images/flags/4/sdn.png"},{"Rank":113,"Name":"Sudan","TotalPoints":297.13,"PreviousPoints":304,"MovePosition":-1,"FlagUrl":"http://img.fifa.com/images/flags/4/sdn.png"},{"Rank":114,"Name":"Syria","TotalPoints":290.67,"PreviousPoints":293,"MovePosition":1,"FlagUrl":"http://img.fifa.com/images/flags/4/syr.png"},{"Rank":115,"Name":"Cuba","TotalPoints":290.01,"PreviousPoints":390,"MovePosition":-23,"FlagUrl":"http://img.fifa.com/images/flags/4/cub.png"},{"Rank":116,"Name":"St. Kitts and Nevis","TotalPoints":285.34,"PreviousPoints":284,"MovePosition":1,"FlagUrl":"http://img.fifa.com/images/flags/4/skn.png"},{"Rank":116,"Name":"Faroe Islands","TotalPoints":285.14,"PreviousPoints":285,"MovePosition":0,"FlagUrl":"http://img.fifa.com/images/flags/4/fro.png"},{"Rank":116,"Name":"Gambia","TotalPoints":284.52,"PreviousPoints":280,"MovePosition":2,"FlagUrl":"http://img.fifa.com/images/flags/4/gam.png"},{"Rank":119,"Name":"New Zealand","TotalPoints":271.14,"PreviousPoints":271,"MovePosition":0,"FlagUrl":"http://img.fifa.com/images/flags/4/nzl.png"},{"Rank":120,"Name":"Kenya","TotalPoints":269.0,"PreviousPoints":240,"MovePosition":13,"FlagUrl":"http://img.fifa.com/images/flags/4/ken.png"},{"Rank":121,"Name":"Namibia","TotalPoints":264.15,"PreviousPoints":264,"MovePosition":0,"FlagUrl":"http://img.fifa.com/images/flags/4/nam.png"},{"Rank":122,"Name":"Thailand","TotalPoints":261.63,"PreviousPoints":243,"MovePosition":10,"FlagUrl":"http://img.fifa.com/images/flags/4/tha.png"},{"Rank":123,"Name":"Liberia","TotalPoints":258.03,"PreviousPoints":258,"MovePosition":0,"FlagUrl":"http://img.fifa.com/images/flags/4/lbr.png"},{"Rank":124,"Name":"Benin","TotalPoints":256.56,"PreviousPoints":257,"MovePosition":0,"FlagUrl":"http://img.fifa.com/images/flags/4/ben.png"},{"Rank":125,"Name":"Congo DR","TotalPoints":253.55,"PreviousPoints":254,"MovePosition":0,"FlagUrl":"http://img.fifa.com/images/flags/4/cod.png"},{"Rank":125,"Name":"Suriname","TotalPoints":254.13,"PreviousPoints":261,"MovePosition":-3,"FlagUrl":"http://img.fifa.com/images/flags/4/sur.png"},{"Rank":127,"Name":"Cyprus","TotalPoints":253.28,"PreviousPoints":253,"MovePosition":-1,"FlagUrl":"http://img.fifa.com/images/flags/4/cyp.png"},{"Rank":128,"Name":"Luxembourg","TotalPoints":251.78,"PreviousPoints":252,"MovePosition":-1,"FlagUrl":"http://img.fifa.com/images/flags/4/lux.png"},{"Rank":129,"Name":"Central African Republic","TotalPoints":250.75,"PreviousPoints":251,"MovePosition":-1,"FlagUrl":"http://img.fifa.com/images/flags/4/cta.png"},{"Rank":130,"Name":"United Arab Emirates","TotalPoints":249.83,"PreviousPoints":265,"MovePosition":-10,"FlagUrl":"http://img.fifa.com/images/flags/4/uae.png"},{"Rank":131,"Name":"Dominican Republic","TotalPoints":246.62,"PreviousPoints":247,"MovePosition":-2,"FlagUrl":"http://img.fifa.com/images/flags/4/dom.png"},{"Rank":132,"Name":"Liechtenstein","TotalPoints":245.81,"PreviousPoints":246,"MovePosition":-2,"FlagUrl":"http://img.fifa.com/images/flags/4/lie.png"},{"Rank":133,"Name":"Congo","TotalPoints":244.79,"PreviousPoints":245,"MovePosition":-2,"FlagUrl":"http://img.fifa.com/images/flags/4/cgo.png"},{"Rank":134,"Name":"Grenada","TotalPoints":241.39,"PreviousPoints":309,"MovePosition":-28,"FlagUrl":"http://img.fifa.com/images/flags/4/grn.png"},{"Rank":135,"Name":"Ethiopia","TotalPoints":230.41,"PreviousPoints":225,"MovePosition":2,"FlagUrl":"http://img.fifa.com/images/flags/4/eth.png"},{"Rank":136,"Name":"Moldova","TotalPoints":229.47,"PreviousPoints":229,"MovePosition":-1,"FlagUrl":"http://img.fifa.com/images/flags/4/mda.png"},{"Rank":137,"Name":"Tanzania","TotalPoints":224.01,"PreviousPoints":228,"MovePosition":-1,"FlagUrl":"http://img.fifa.com/images/flags/4/tan.png"},{"Rank":138,"Name":"Kazakhstan","TotalPoints":220.32,"PreviousPoints":219,"MovePosition":0,"FlagUrl":"http://img.fifa.com/images/flags/4/kaz.png"},{"Rank":139,"Name":"Tajikistan","TotalPoints":208.36,"PreviousPoints":207,"MovePosition":0,"FlagUrl":"http://img.fifa.com/images/flags/4/tjk.png"},{"Rank":140,"Name":"Burundi","TotalPoints":203.06,"PreviousPoints":174,"MovePosition":5,"FlagUrl":"http://img.fifa.com/images/flags/4/bdi.png"},{"Rank":141,"Name":"Belize","TotalPoints":193.86,"PreviousPoints":194,"MovePosition":-1,"FlagUrl":"http://img.fifa.com/images/flags/4/blz.png"},{"Rank":142,"Name":"Indonesia","TotalPoints":189.05,"PreviousPoints":176,"MovePosition":2,"FlagUrl":"http://img.fifa.com/images/flags/4/idn.png"},{"Rank":143,"Name":"Chad","TotalPoints":187.54,"PreviousPoints":188,"MovePosition":-2,"FlagUrl":"http://img.fifa.com/images/flags/4/cha.png"},{"Rank":144,"Name":"St. Vincent and the Grenadines","TotalPoints":170.01,"PreviousPoints":170,"MovePosition":2,"FlagUrl":"http://img.fifa.com/images/flags/4/vin.png"},{"Rank":145,"Name":"Singapore","TotalPoints":165.19,"PreviousPoints":146,"MovePosition":7,"FlagUrl":"http://img.fifa.com/images/flags/4/sin.png"},{"Rank":146,"Name":"Turkmenistan","TotalPoints":163.79,"PreviousPoints":164,"MovePosition":1,"FlagUrl":"http://img.fifa.com/images/flags/4/tkm.png"},{"Rank":147,"Name":"Lesotho","TotalPoints":160.47,"PreviousPoints":160,"MovePosition":1,"FlagUrl":"http://img.fifa.com/images/flags/4/les.png"},{"Rank":148,"Name":"Malaysia","TotalPoints":154.22,"PreviousPoints":140,"MovePosition":7,"FlagUrl":"http://img.fifa.com/images/flags/4/mas.png"},{"Rank":149,"Name":"Samoa","TotalPoints":148.75,"PreviousPoints":0,"MovePosition":55,"FlagUrl":"http://img.fifa.com/images/flags/4/sam.png"},{"Rank":150,"Name":"Equatorial Guinea","TotalPoints":147.91,"PreviousPoints":148,"MovePosition":1,"FlagUrl":"http://img.fifa.com/images/flags/4/eqg.png"},{"Rank":151,"Name":"Yemen","TotalPoints":145.63,"PreviousPoints":153,"MovePosition":-1,"FlagUrl":"http://img.fifa.com/images/flags/4/yem.png"},{"Rank":151,"Name":"Curaçao","TotalPoints":145.9,"PreviousPoints":154,"MovePosition":-2,"FlagUrl":"http://img.fifa.com/images/flags/4/cuw.png"},{"Rank":153,"Name":"Nepal","TotalPoints":143.97,"PreviousPoints":177,"MovePosition":-10,"FlagUrl":"http://img.fifa.com/images/flags/4/nep.png"},{"Rank":154,"Name":"Bahamas","TotalPoints":140.5,"PreviousPoints":141,"MovePosition":-1,"FlagUrl":"http://img.fifa.com/images/flags/4/bah.png"},{"Rank":154,"Name":"Nicaragua","TotalPoints":140.59,"PreviousPoints":141,"MovePosition":-1,"FlagUrl":"http://img.fifa.com/images/flags/4/nca.png"},{"Rank":156,"Name":"Malta","TotalPoints":139.72,"PreviousPoints":140,"MovePosition":-1,"FlagUrl":"http://img.fifa.com/images/flags/4/mlt.png"},{"Rank":157,"Name":"Bangladesh","TotalPoints":137.58,"PreviousPoints":181,"MovePosition":-15,"FlagUrl":"http://img.fifa.com/images/flags/4/ban.png"},{"Rank":158,"Name":"Palestine","TotalPoints":137.38,"PreviousPoints":113,"MovePosition":6,"FlagUrl":"http://img.fifa.com/images/flags/4/ple.png"},{"Rank":159,"Name":"Philippines","TotalPoints":135.95,"PreviousPoints":130,"MovePosition":0,"FlagUrl":"http://img.fifa.com/images/flags/4/phi.png"},{"Rank":160,"Name":"Madagascar","TotalPoints":134.87,"PreviousPoints":135,"MovePosition":-3,"FlagUrl":"http://img.fifa.com/images/flags/4/mad.png"},{"Rank":161,"Name":"Fiji","TotalPoints":133.45,"PreviousPoints":133,"MovePosition":-3,"FlagUrl":"http://img.fifa.com/images/flags/4/fij.png"},{"Rank":162,"Name":"India","TotalPoints":131.37,"PreviousPoints":119,"MovePosition":0,"FlagUrl":"http://img.fifa.com/images/flags/4/ind.png"},{"Rank":163,"Name":"Guinea-Bissau","TotalPoints":120.65,"PreviousPoints":129,"MovePosition":-3,"FlagUrl":"http://img.fifa.com/images/flags/4/gnb.png"},{"Rank":164,"Name":"Aruba","TotalPoints":119.8,"PreviousPoints":92,"MovePosition":8,"FlagUrl":"http://img.fifa.com/images/flags/4/aru.png"},{"Rank":165,"Name":"Barbados","TotalPoints":119.16,"PreviousPoints":125,"MovePosition":-4,"FlagUrl":"http://img.fifa.com/images/flags/4/brb.png"},{"Rank":166,"Name":"New Caledonia","TotalPoints":116.16,"PreviousPoints":116,"MovePosition":-3,"FlagUrl":"http://img.fifa.com/images/flags/4/ncl.png"},{"Rank":167,"Name":"Chinese Taipei","TotalPoints":114.43,"PreviousPoints":109,"MovePosition":-2,"FlagUrl":"http://img.fifa.com/images/flags/4/tpe.png"},{"Rank":168,"Name":"Mongolia","TotalPoints":105.6,"PreviousPoints":106,"MovePosition":-2,"FlagUrl":"http://img.fifa.com/images/flags/4/mng.png"},{"Rank":169,"Name":"Hong Kong","TotalPoints":105.22,"PreviousPoints":105,"MovePosition":-1,"FlagUrl":"http://img.fifa.com/images/flags/4/hkg.png"},{"Rank":170,"Name":"Cambodia","TotalPoints":101.38,"PreviousPoints":103,"MovePosition":-1,"FlagUrl":"http://img.fifa.com/images/flags/4/cam.png"},{"Rank":171,"Name":"Dominica","TotalPoints":100.36,"PreviousPoints":90,"MovePosition":2,"FlagUrl":"http://img.fifa.com/images/flags/4/dma.png"},{"Rank":172,"Name":"Myanmar","TotalPoints":98.99,"PreviousPoints":103,"MovePosition":-3,"FlagUrl":"http://img.fifa.com/images/flags/4/mya.png"},{"Rank":173,"Name":"Maldives","TotalPoints":98.44,"PreviousPoints":106,"MovePosition":-7,"FlagUrl":"http://img.fifa.com/images/flags/4/mdv.png"},{"Rank":174,"Name":"Laos","TotalPoints":95.93,"PreviousPoints":86,"MovePosition":1,"FlagUrl":"http://img.fifa.com/images/flags/4/lao.png"},{"Rank":174,"Name":"Vanuatu","TotalPoints":95.79,"PreviousPoints":96,"MovePosition":-3,"FlagUrl":"http://img.fifa.com/images/flags/4/van.png"},{"Rank":176,"Name":"Tonga","TotalPoints":87.55,"PreviousPoints":3,"MovePosition":26,"FlagUrl":"http://img.fifa.com/images/flags/4/tga.png"},{"Rank":177,"Name":"Afghanistan","TotalPoints":85.32,"PreviousPoints":77,"MovePosition":1,"FlagUrl":"http://img.fifa.com/images/flags/4/afg.png"},{"Rank":178,"Name":"US Virgin Islands","TotalPoints":81.62,"PreviousPoints":82,"MovePosition":-1,"FlagUrl":"http://img.fifa.com/images/flags/4/vir.png"},{"Rank":179,"Name":"Pakistan","TotalPoints":75.9,"PreviousPoints":87,"MovePosition":-5,"FlagUrl":"http://img.fifa.com/images/flags/4/pak.png"},{"Rank":180,"Name":"Solomon Islands","TotalPoints":74.62,"PreviousPoints":75,"MovePosition":-1,"FlagUrl":"http://img.fifa.com/images/flags/4/sol.png"},{"Rank":180,"Name":"Swaziland","TotalPoints":74.74,"PreviousPoints":75,"MovePosition":-1,"FlagUrl":"http://img.fifa.com/images/flags/4/swz.png"},{"Rank":180,"Name":"Sri Lanka","TotalPoints":75.43,"PreviousPoints":85,"MovePosition":-4,"FlagUrl":"http://img.fifa.com/images/flags/4/sri.png"},{"Rank":183,"Name":"Cayman Islands","TotalPoints":73.99,"PreviousPoints":74,"MovePosition":-2,"FlagUrl":"http://img.fifa.com/images/flags/4/cay.png"},{"Rank":184,"Name":"Tahiti","TotalPoints":73.34,"PreviousPoints":73,"MovePosition":-2,"FlagUrl":"http://img.fifa.com/images/flags/4/tah.png"},{"Rank":185,"Name":"St. Lucia","TotalPoints":65.19,"PreviousPoints":65,"MovePosition":-1,"FlagUrl":"http://img.fifa.com/images/flags/4/lca.png"},{"Rank":186,"Name":"American Samoa","TotalPoints":60.71,"PreviousPoints":0,"MovePosition":18,"FlagUrl":"http://img.fifa.com/images/flags/4/asa.png"},{"Rank":187,"Name":"Comoros","TotalPoints":54.96,"PreviousPoints":55,"MovePosition":-1,"FlagUrl":"http://img.fifa.com/images/flags/4/com.png"},{"Rank":188,"Name":"Seychelles","TotalPoints":52.54,"PreviousPoints":69,"MovePosition":-5,"FlagUrl":"http://img.fifa.com/images/flags/4/sey.png"},{"Rank":189,"Name":"Somalia","TotalPoints":47.2,"PreviousPoints":51,"MovePosition":-2,"FlagUrl":"http://img.fifa.com/images/flags/4/som.png"},{"Rank":190,"Name":"Eritrea","TotalPoints":45.49,"PreviousPoints":65,"MovePosition":-6,"FlagUrl":"http://img.fifa.com/images/flags/4/eri.png"},{"Rank":191,"Name":"Kyrgyzstan","TotalPoints":41.9,"PreviousPoints":42,"MovePosition":-3,"FlagUrl":"http://img.fifa.com/images/flags/4/kgz.png"},{"Rank":192,"Name":"Guam","TotalPoints":35.85,"PreviousPoints":36,"MovePosition":-3,"FlagUrl":"http://img.fifa.com/images/flags/4/gum.png"},{"Rank":193,"Name":"Papua New Guinea","TotalPoints":34.0,"PreviousPoints":34,"MovePosition":-3,"FlagUrl":"http://img.fifa.com/images/flags/4/png.png"},{"Rank":194,"Name":"Mauritius","TotalPoints":32.35,"PreviousPoints":32,"MovePosition":-3,"FlagUrl":"http://img.fifa.com/images/flags/4/mri.png"},{"Rank":195,"Name":"Cook Islands","TotalPoints":27.91,"PreviousPoints":10,"MovePosition":1,"FlagUrl":"http://img.fifa.com/images/flags/4/cok.png"},{"Rank":196,"Name":"São Tomé e Príncipe","TotalPoints":26.66,"PreviousPoints":27,"MovePosition":-4,"FlagUrl":"http://img.fifa.com/images/flags/4/stp.png"},{"Rank":197,"Name":"Macau","TotalPoints":25.72,"PreviousPoints":26,"MovePosition":-4,"FlagUrl":"http://img.fifa.com/images/flags/4/mac.png"},{"Rank":198,"Name":"Djibouti","TotalPoints":24.91,"PreviousPoints":5,"MovePosition":2,"FlagUrl":"http://img.fifa.com/images/flags/4/dji.png"},{"Rank":199,"Name":"British Virgin Islands","TotalPoints":23.12,"PreviousPoints":23,"MovePosition":-5,"FlagUrl":"http://img.fifa.com/images/flags/4/vgb.png"},{"Rank":200,"Name":"Turks and Caicos Islands","TotalPoints":12.75,"PreviousPoints":13,"MovePosition":-5,"FlagUrl":"http://img.fifa.com/images/flags/4/tca.png"},{"Rank":201,"Name":"Anguilla","TotalPoints":8.8,"PreviousPoints":9,"MovePosition":-4,"FlagUrl":"http://img.fifa.com/images/flags/4/aia.png"},{"Rank":202,"Name":"Bhutan","TotalPoints":6.07,"PreviousPoints":6,"MovePosition":-4,"FlagUrl":"http://img.fifa.com/images/flags/4/bhu.png"},{"Rank":202,"Name":"Brunei Darussalam","TotalPoints":6.07,"PreviousPoints":6,"MovePosition":-4,"FlagUrl":"http://img.fifa.com/images/flags/4/bru.png"},{"Rank":204,"Name":"Mauritania","TotalPoints":4.3,"PreviousPoints":4,"MovePosition":-3,"FlagUrl":"http://img.fifa.com/images/flags/4/mtn.png"},{"Rank":205,"Name":"Timor-Leste","TotalPoints":1.7,"PreviousPoints":2,"MovePosition":-2,"FlagUrl":"http://img.fifa.com/images/flags/4/tls.png"},{"Rank":206,"Name":"Andorra","TotalPoints":0.0,"PreviousPoints":0,"MovePosition":-2,"FlagUrl":"http://img.fifa.com/images/flags/4/and.png"},{"Rank":206,"Name":"Montserrat","TotalPoints":0.0,"PreviousPoints":0,"MovePosition":-2,"FlagUrl":"http://img.fifa.com/images/flags/4/msr.png"},{"Rank":206,"Name":"San Marino","TotalPoints":0.0,"PreviousPoints":0,"MovePosition":-2,"FlagUrl":"http://img.fifa.com/images/flags/4/smr.png"}],"Id":209,"Date":"2011-12-21T00:00:00"}